unitstyle/__init__.py
unitstyle/unitstyle.py
unitstyle-1.0.1.dist-info/DESCRIPTION.rst
unitstyle-1.0.1.dist-info/METADATA
unitstyle-1.0.1.dist-info/RECORD
unitstyle-1.0.1.dist-info/WHEEL
unitstyle-1.0.1.dist-info/metadata.json
unitstyle-1.0.1.dist-info/top_level.txt
