Metadata-Version: 2.0
Name: unitstyle
Version: 1.0.1
Summary: Adds various style choices to unittest output
Home-page: https://github.com/pzl/py_unitstyle
Author: Dan Panzarella
Author-email: dan@panzarel.la
License: MIT
Keywords: test testing unittest unitstyle console development
Platform: UNKNOWN
Classifier: Development Status :: 4 - Beta
Classifier: Environment :: Console
Classifier: Intended Audience :: Developers
Classifier: License :: OSI Approved :: MIT License
Classifier: Programming Language :: Python :: 2
Classifier: Programming Language :: Python :: 2.6
Classifier: Programming Language :: Python :: 2.7
Classifier: Programming Language :: Python :: 3
Classifier: Programming Language :: Python :: 3.3
Classifier: Programming Language :: Python :: 3.4
Classifier: Programming Language :: Python :: 3.5
Classifier: Topic :: Software Development :: Testing
